mcp_client/__init__.py
mcp_client/__main__.py
mcp_client/weather_client.py
mcp_client/weather_server.py
mcp_client4-0.1.0.dist-info/METADATA
mcp_client4-0.1.0.dist-info/WHEEL
mcp_client4-0.1.0.dist-info/entry_points.txt
mcp_client4-0.1.0.dist-info/top_level.txt
mcp_client4-0.1.0.dist-info/RECORD
