Metadata-Version: 2.4
Name: mcp-client4
Version: 0.1.0
Summary: Add your description here
Requires-Python: >=3.11
Requires-Dist: httpx>=0.28.1
Requires-Dist: mcp>=1.7.1
Requires-Dist: openai>=1.77.0
Requires-Dist: python-dotenv>=1.1.0
